cryptie/__init__.py
cryptie/log_file_utils.py
cryptie/gpg/__init__.py
cryptie/gpg/card_edit.py
cryptie/gpg/card_status.py
cryptie/gpg/change_pin.py
cryptie/gpg/cryptography.py
cryptie/gpg/home.py
cryptie/gpg/keys.py
cryptie/gpg/shell.py
cryptie-0.0.2.dist-info/licenses/LICENSE
cryptie-0.0.2.dist-info/METADATA
cryptie-0.0.2.dist-info/WHEEL
cryptie-0.0.2.dist-info/entry_points.txt
cryptie-0.0.2.dist-info/top_level.txt
cryptie-0.0.2.dist-info/RECORD
