Metadata-Version: 2.4
Name: cryptie
Version: 0.0.2
Summary: Simple file encryption using PGP cards (e.g. Yubikeys)
License-File: LICENSE
Dynamic: license-file
